simulation/booth_mult.v
module booth_mult(A, B, clk, load, rst, Y);

   input [7:0] A;
   input [7:0] B;
   input       clk;
   input       load;
   input       rst;
   output reg [15:0] Y;

   reg		 load_lock = 0;
   reg [7:0] 	 A_reg;
   reg [15:0] 	 B_reg;
   reg [15:0] 	 Y_reg;
   reg [3:0] 	 count;

   always @(posedge clk)
     begin
	if (rst == 1)
	  begin
	     A_reg <= 0;
	     B_reg <= 0;
	     Y <= 0;
	     count <= 0;
	     Y_reg <= 0;
	  end
	// load?
	else if (load_lock != 1 && load == 1)
	  begin
	     A_reg <= A;
	     B_reg[7:0] <= B;
	     B_reg[15:8] <= 0;
	     count <= 0;
	     Y_reg <= 0;
	  end
	else if (load != 1)
	  begin
	     if (count < 8) begin
		load_lock <= 1;
		if (A[count])
		  Y_reg <= Y_reg + B_reg;
		B_reg <= B_reg << 1;
		count <= count + 1;
	     end
	     else
	       begin
		  Y <= Y_reg;
		  load_lock <= 0;
	       end // else: !if(count < 8)
	  end // if (load != 1)
     end // always @ (posedge clk)
endmodule // booth_mult

simulation/boothmult_tb.v
`timescale 1ns/1ns

module boothmult_tb;

   reg [7:0] A;
   reg [7:0] B;
   reg 	     clk = 0;
   reg 	     load;
   reg 	     rst = 1;
   wire [15:0] Y;

   booth_mult dut (A, B, clk, load, rst, Y);

   initial
     begin
	$dumpfile("boothmult_tb.vcd");
	$dumpvars(0, boothmult_tb);
     end

   always
     #2 clk <= ~clk;

   initial
     begin
	#10;
	rst <= 0;
	#4;
	A <= 20;
	B <= 30;
	load <= 1;
	#10;
	load <= 0;
	# 50;
	$finish;
     end // initial begin
endmodule // boothmult_tb

simulation/boothmult_tb.vcd
$date
	Sun Oct  7 18:26:33 2018
$end
$version
	Icarus Verilog
$end
$timescale
	1ns
$end
$scope module boothmult_tb $end
$var wire 16 ! Y [15:0] $end
$var reg 8 " A [7:0] $end
$var reg 8 # B [7:0] $end
$var reg 1 $ clk $end
$var reg 1 % load $end
$var reg 1 & rst $end
$scope module dut $end
$var wire 8 ' A [7:0] $end
$var wire 8 ( B [7:0] $end
$var wire 1 ) clk $end
$var wire 1 * load $end
$var wire 1 + rst $end
$var reg 8 , A_reg [7:0] $end
$var reg 16 - B_reg [15:0] $end
$var reg 16 . Y [15:0] $end
$var reg 16 / Y_reg [15:0] $end
$var reg 4 0 count [3:0] $end
$var reg 1 1 load_lock $end
$upscope $end
$upscope $end
$enddefinitions $end
#0
$dumpvars
01
bx 0
bx /
bx .
bx -
bx ,
1+
x*
0)
bx (
bx '
1&
x%
0$
bx #
bx "
bx !
$end
#2
b0 /
b0 0
b0 .
b0 !
b0 -
b0 ,
1$
1)
#4
0$
0)
#6
1$
1)
#8
0$
0)
#10
1$
1)
0&
0+
#12
0$
0)
#14
b11110 -
b10100 ,
1$
1)
1%
1*
b11110 #
b11110 (
b10100 "
b10100 '
#16
0$
0)
#18
b11110 -
1$
1)
#20
0$
0)
#22
b11110 -
1$
1)
#24
0$
0)
0%
0*
#26
b1 0
b111100 -
11
1$
1)
#28
0$
0)
#30
b10 0
b1111000 -
1$
1)
#32
0$
0)
#34
b11 0
b11110000 -
b1111000 /
1$
1)
#36
0$
0)
#38
b100 0
b111100000 -
1$
1)
#40
0$
0)
#42
b101 0
b1111000000 -
b1001011000 /
1$
1)
#44
0$
0)
#46
b110 0
b11110000000 -
1$
1)
#48
0$
0)
#50
b111 0
b111100000000 -
1$
1)
#52
0$
0)
#54
b1000 0
b1111000000000 -
1$
1)
#56
0$
0)
#58
01
b1001011000 .
b1001011000 !
1$
1)
