simulation/full_adder.v
module full_adder(A, B, Cin, S, Cout);
   input A, B, Cin;
   output S, Cout;

   wire   xor1;
   wire   and1;
   wire   and2;

   xor (xor1, A, B);
   xor (S, xor1, Cin);
   and (and1, xor1, Cin);
   and (and2, A, B);
   or  (Cout, and1, and2);

endmodule // full_adder

simulation/full_adder_tb.v
`timescale 1ns/1ns

module full_adder_tb;

   reg A, B, Cin; 
   wire S, Cout;
   integer i, j, k;
   full_adder dut(A, B, Cin, S, Cout);

   initial
     begin
	$dumpfile("full_adder_tb.vcd");
	$dumpvars(0, full_adder_tb);
     end

   initial
     begin
	A <= 0;
	B <= 0;
	Cin <= 0;
	#5;
	for (i = 0; i < 2; i = i + 1) begin
	   for (j = 0; j < 2; j = j + 1) begin
	      for (k = 0; k < 2; k = k + 1) begin
		 #5 Cin <= ~Cin;
	      end
	      #5 B <= ~B;
	   end
	   #5 A <= ~A;
	end
	#10 $finish;
     end // initial begin

endmodule // full_adder_tb

simulation/full_adder_tb.vcd
$date
	Sat Oct  6 14:00:34 2018
$end
$version
	Icarus Verilog
$end
$timescale
	1ns
$end
$scope module full_adder_tb $end
$var wire 1 ! Cout $end
$var wire 1 " S $end
$var reg 1 # A $end
$var reg 1 $ B $end
$var reg 1 % Cin $end
$var integer 32 & i [31:0] $end
$var integer 32 ' j [31:0] $end
$var integer 32 ( k [31:0] $end
$scope module dut $end
$var wire 1 ) A $end
$var wire 1 * B $end
$var wire 1 + Cin $end
$var wire 1 ! Cout $end
$var wire 1 " S $end
$var wire 1 , and1 $end
$var wire 1 - and2 $end
$var wire 1 . xor1 $end
$upscope $end
$upscope $end
$enddefinitions $end
#0
$dumpvars
0.
0-
0,
0+
0*
0)
bx (
bx '
bx &
0%
0$
0#
0"
0!
$end
#5
b0 (
b0 '
b0 &
#10
1"
1%
1+
b1 (
#15
0"
0%
0+
b10 (
#20
1"
1.
1$
1*
b0 (
b1 '
#25
1!
0"
1,
1%
1+
b1 (
#30
0!
1"
0,
0%
0+
b10 (
#35
0"
0.
0$
0*
b10 '
#40
1"
1.
1#
1)
b0 (
b0 '
b1 &
#45
1!
0"
1,
1%
1+
b1 (
#50
0!
1"
0,
0%
0+
b10 (
#55
0"
1!
0.
1-
1$
1*
b0 (
b1 '
#60
1"
1%
1+
b1 (
#65
0"
0%
0+
b10 (
#70
1"
0!
1.
0-
0$
0*
b10 '
#75
0"
0.
0#
0)
b10 &
